README.md
setup.py
grew/__init__.py
grew/graph.py
grew/grew.py
grew/network.py
grew/utils.py
grew.egg-info/PKG-INFO
grew.egg-info/SOURCES.txt
grew.egg-info/dependency_links.txt
grew.egg-info/top_level.txt